gradio_molgallery3d/__init__.py
gradio_molgallery3d/molgallery3d.py
gradio_molgallery3d/molgallery3d.pyi
gradio_molgallery3d/templates/component/index.js
gradio_molgallery3d/templates/component/style.css
gradio_molgallery3d-1.1.0.dist-info/METADATA
gradio_molgallery3d-1.1.0.dist-info/WHEEL
gradio_molgallery3d-1.1.0.dist-info/licenses/LICENSE
gradio_molgallery3d-1.1.0.dist-info/RECORD
